{
  "timeZone": "America/New_York",
  "dependencies": {},
  "exceptionLogging": "STACKDRIVER",
  "runtimeVersion": "V8",
  "oauthScopes": [
    "https://www.googleapis.com/auth/gmail.modify",
    "https://www.googleapis.com/auth/gmail.addons.execute",
    "https://www.googleapis.com/auth/gmail.addons.current.message.readonly",
    "https://www.googleapis.com/auth/script.external_request",
    "https://www.googleapis.com/auth/script.scriptapp"
  ],
  "gmail": {
    "name": "Counter Pitch",
    "logoUrl": "https://www.gstatic.com/images/branding/product/1x/gmail_2020q4_48dp.png",
    "contextualTriggers": [
      {
        "unconditional": {},
        "onTriggerFunction": "onGmailMessage"
      }
    ],
    "homepageTrigger": {
      "runFunction": "onHomepage"
    }
  }
}
